validibot_cli/__init__.py
validibot_cli/auth.py
validibot_cli/client.py
validibot_cli/config.py
validibot_cli/main.py
validibot_cli/models.py
validibot_cli/commands/__init__.py
validibot_cli/commands/auth.py
validibot_cli/commands/runs.py
validibot_cli/commands/validate.py
validibot_cli/commands/workflows.py
validibot_cli-0.1.5.dist-info/METADATA
validibot_cli-0.1.5.dist-info/WHEEL
validibot_cli-0.1.5.dist-info/entry_points.txt
validibot_cli-0.1.5.dist-info/licenses/LICENSE
validibot_cli-0.1.5.dist-info/RECORD
