Metadata-Version: 2.4
Name: validibot-cli
Version: 0.1.5
Summary: Command-line interface for Validibot - your automated data validation assistant.
Project-URL: Homepage, https://validibot.com
Project-URL: Documentation, https://docs.validibot.com
Project-URL: Repository, https://github.com/danielmcquillen/validibot-cli
Project-URL: Issues, https://github.com/danielmcquillen/validibot-cli/issues
Author-email: Daniel McQuillen <daniel@validibot.com>
Maintainer-email: Daniel McQuillen <daniel@validibot.com>
License: MIT
License-File: LICENSE
Keywords: automation,cli,data-quality,energyplus,fmu,simulation,validation
Classifier: Development Status :: 3 - Alpha
Classifier: Environment :: Console
Classifier: Intended Audience :: Developers
Classifier: License :: OSI Approved :: MIT License
Classifier: Operating System :: OS Independent
Classifier: Programming Language :: Python :: 3
Classifier: Programming Language :: Python :: 3.10
Classifier: Programming Language :: Python :: 3.11
Classifier: Programming Language :: Python :: 3.12
Classifier: Programming Language :: Python :: 3.13
Classifier: Topic :: Scientific/Engineering
Classifier: Topic :: Software Development :: Quality Assurance
Requires-Python: >=3.10
Requires-Dist: httpx>=0.28.0
Requires-Dist: keyring>=25.5.0
Requires-Dist: platformdirs>=4.0.0
Requires-Dist: pydantic-settings>=2.7.0
Requires-Dist: pydantic>=2.10.0
Requires-Dist: rich>=13.9.0
Requires-Dist: typer>=0.15.0
Provides-Extra: dev
Requires-Dist: mypy>=1.14.0; extra == 'dev'
Requires-Dist: pytest-cov>=6.0.0; extra == 'dev'
Requires-Dist: pytest>=8.0.0; extra == 'dev'
Requires-Dist: ruff>=0.8.0; extra == 'dev'
